dastab/__init__.py
dastab-0.0.1.dist-info/METADATA
dastab-0.0.1.dist-info/WHEEL
dastab-0.0.1.dist-info/licenses/LICENSE
dastab-0.0.1.dist-info/RECORD
