Metadata-Version: 2.1
Name: dastab
Version: 0.0.1
Summary: dastab, save your data where you want and collect it as you like
Project-URL: Homepage, https://github.com/wogra-ag/dastab
Project-URL: Documentation, https://wogra-ag.github.io/dastab
Author-email: WOGRA AG <info@wogra.com>
License-File: LICENSE
Classifier: License :: OSI Approved :: MIT License
Classifier: Programming Language :: Python
Classifier: Programming Language :: Python :: 3
Requires-Python: >=3.7
Requires-Dist: pydantic!=1.7,!=1.7.1,!=1.7.2,!=1.7.3,!=1.8,!=1.8.1,<2.0.0,>=1.6.2
Requires-Dist: starlette==0.20.4
Provides-Extra: all
Requires-Dist: email-validator<2.0.0,>=1.1.1; extra == 'all'
Requires-Dist: itsdangerous<3.0.0,>=1.1.0; extra == 'all'
Requires-Dist: jinja2<4.0.0,>=2.11.2; extra == 'all'
Requires-Dist: orjson<4.0.0,>=3.2.1; extra == 'all'
Requires-Dist: python-multipart<0.0.6,>=0.0.5; extra == 'all'
Requires-Dist: pyyaml<7.0.0,>=5.3.1; extra == 'all'
Requires-Dist: requests<3.0.0,>=2.24.0; extra == 'all'
Requires-Dist: ujson!=4.0.2,!=4.1.0,!=4.2.0,!=4.3.0,!=5.0.0,!=5.1.0,<6.0.0,>=4.0.1; extra == 'all'
Requires-Dist: uvicorn[standard]<0.19.0,>=0.12.0; extra == 'all'
Provides-Extra: dev
Requires-Dist: autoflake<2.0.0,>=1.4.0; extra == 'dev'
Requires-Dist: flake8<6.0.0,>=3.8.3; extra == 'dev'
Requires-Dist: pre-commit<3.0.0,>=2.17.0; extra == 'dev'
Requires-Dist: uvicorn[standard]<0.19.0,>=0.12.0; extra == 'dev'
Provides-Extra: doc
Requires-Dist: mdx-include<2.0.0,>=1.4.1; extra == 'doc'
Requires-Dist: mkdocs-markdownextradata-plugin<0.3.0,>=0.1.7; extra == 'doc'
Requires-Dist: mkdocs-material<9.0.0,>=8.1.4; extra == 'doc'
Requires-Dist: mkdocs<2.0.0,>=1.1.2; extra == 'doc'
Requires-Dist: pyyaml<7.0.0,>=5.3.1; extra == 'doc'
Requires-Dist: typer[all]<0.7.0,>=0.6.1; extra == 'doc'
Provides-Extra: test
Requires-Dist: anyio[trio]<4.0.0,>=3.2.1; extra == 'test'
Requires-Dist: black==22.8.0; extra == 'test'
Requires-Dist: databases[sqlite]<0.7.0,>=0.3.2; extra == 'test'
Requires-Dist: email-validator<2.0.0,>=1.1.1; extra == 'test'
Requires-Dist: flake8<6.0.0,>=3.8.3; extra == 'test'
Requires-Dist: flask<3.0.0,>=1.1.2; extra == 'test'
Requires-Dist: httpx<0.24.0,>=0.23.0; extra == 'test'
Requires-Dist: isort<6.0.0,>=5.0.6; extra == 'test'
Requires-Dist: mypy==0.971; extra == 'test'
Requires-Dist: orjson<4.0.0,>=3.2.1; extra == 'test'
Requires-Dist: passlib[bcrypt]<2.0.0,>=1.7.2; extra == 'test'
Requires-Dist: peewee<4.0.0,>=3.13.3; extra == 'test'
Requires-Dist: pytest-cov<4.0.0,>=2.12.0; extra == 'test'
Requires-Dist: pytest<8.0.0,>=7.1.3; extra == 'test'
Requires-Dist: python-jose[cryptography]<4.0.0,>=3.3.0; extra == 'test'
Requires-Dist: python-multipart<0.0.6,>=0.0.5; extra == 'test'
Requires-Dist: pyyaml<7.0.0,>=5.3.1; extra == 'test'
Requires-Dist: requests<3.0.0,>=2.24.0; extra == 'test'
Requires-Dist: sqlalchemy<=1.4.41,>=1.3.18; extra == 'test'
Requires-Dist: types-orjson==3.6.2; extra == 'test'
Requires-Dist: types-ujson==5.4.0; extra == 'test'
Requires-Dist: ujson!=4.0.2,!=4.1.0,!=4.2.0,!=4.3.0,!=5.0.0,!=5.1.0,<6.0.0,>=4.0.1; extra == 'test'
